KitFun/KitFun.py
KitFun/__init__.py
kitfun-0.1.1.dist-info/licenses/LICENSE
kitfun-0.1.1.dist-info/METADATA
kitfun-0.1.1.dist-info/WHEEL
kitfun-0.1.1.dist-info/top_level.txt
kitfun-0.1.1.dist-info/RECORD
