Metadata-Version: 2.4
Name: KitFun
Version: 0.1.1
Summary: 一个功能强大的 Python 装饰器工具包 | A powerful Python decorator toolkit
Home-page: https://github.com/cxfjh/FunKit
Author: cxfjh
Author-email: 2449579731@qq.com
License: MIT
Keywords: decorator,toolkit,fun,kit,funkit,funkit,装饰器,工具包,函数,函数式编程,KitFun
Classifier: Programming Language :: Python :: 3
Classifier: License :: OSI Approved :: MIT License
Classifier: Operating System :: OS Independent
Requires-Python: >=3.6
License-File: LICENSE
Requires-Dist: psutil
Dynamic: author
Dynamic: author-email
Dynamic: classifier
Dynamic: description
Dynamic: description-content-type
Dynamic: home-page
Dynamic: keywords
Dynamic: license
Dynamic: license-file
Dynamic: requires-dist
Dynamic: requires-python
Dynamic: summary
